providers/__init__.py
providers/anthropic_provider.py
providers/deepseek_provider.py
providers/fireworks_provider.py
providers/ollama_provider.py
providers/openai_provider.py
sec_llmfactory-0.1.1.dist-info/METADATA
sec_llmfactory-0.1.1.dist-info/WHEEL
sec_llmfactory-0.1.1.dist-info/top_level.txt
sec_llmfactory-0.1.1.dist-info/RECORD
