Metadata-Version: 2.1
Name: sec_llmfactory
Version: 0.1.1
Summary: LLMFactory is a modular framework built on LangChain, offering a factory-based approach for seamless integration and management of Large Language Models (LLMs) from multiple providers, ensuring flexibility, scalability, and maintainability.
Home-page: https://kappa.e-cq.net/linh.vo/llmfactory
Author: Linh Vo
Author-email: linh.vo@e-cq.net
Classifier: Programming Language :: Python :: 3
Classifier: License :: OSI Approved :: MIT License
Classifier: Operating System :: OS Independent
Requires-Python: >=3.9
Requires-Dist: langchain ==0.3.14
Requires-Dist: langchain-anthropic ==0.3.3
Requires-Dist: langchain-fireworks ==0.2.6
Requires-Dist: langchain-ollama ==0.2.2
Requires-Dist: langchain-openai ==0.3.1
Requires-Dist: python-dotenv
